wspr/__init__.py
wspr/blob.py
wspr/channel.py
wspr/client.py
wspr/log.py
wspr/user.py
wspr/wspr.py
wspr-0.0.4.dist-info/AUTHORS.rst
wspr-0.0.4.dist-info/LICENSE
wspr-0.0.4.dist-info/METADATA
wspr-0.0.4.dist-info/WHEEL
wspr-0.0.4.dist-info/top_level.txt
wspr-0.0.4.dist-info/RECORD
