Metadata-Version: 2.1
Name: wspr
Version: 0.0.4
Summary: Mumble client library.
Home-page: https://github.com/ArkadiuszMichalRys/wspr
Author: Arkadiusz Michal Rys
Author-email: Arkadiusz.Michal.Rys@gmail.com
License: MIT license
Keywords: wspr
Platform: UNKNOWN
Classifier: Development Status :: 2 - Pre-Alpha
Classifier: Intended Audience :: Developers
Classifier: License :: OSI Approved :: MIT License
Classifier: Natural Language :: English
Classifier: Programming Language :: Python :: 3
Classifier: Programming Language :: Python :: 3.6
